flowchain/__init__.py
flowchain/chain.py
flowchain/chain_test.py
flowchain-0.0.8.dist-info/LICENSE
flowchain-0.0.8.dist-info/METADATA
flowchain-0.0.8.dist-info/WHEEL
flowchain-0.0.8.dist-info/top_level.txt
flowchain-0.0.8.dist-info/RECORD
