Metadata-Version: 2.1
Name: flowchain
Version: 0.0.8
Summary: Flowchain - Method Chaining for TensorFlow
Home-page: https://github.com/OrigamiDream/flowchain
Author: OrigamiDream
Author-email: hello@origamidream.me
License: MIT
Keywords: machine learning,deep learning,tensorflow,method chaining,extension
Classifier: Development Status :: 4 - Beta
Classifier: Intended Audience :: Developers
Classifier: Topic :: Scientific/Engineering :: Artificial Intelligence
Classifier: License :: OSI Approved :: MIT License
Classifier: Programming Language :: Python :: 3.7
Requires-Python: >=3.7.0
License-File: LICENSE
